{
  "headline": {
    "title": "Ibovespa Hoje Ao Vivo: Confira o que movimenta Bolsa, Dólar e Juros nesta quarta",
    "summary": "Índices futuros dos EUA operam sem força em dia de decisão do Fed",
    "source": "InfoMoney",
    "url": "https://www.infomoney.com.br/mercados/ibovespa-hoje-bolsa-de-valores-ao-vivo-17062026/",
    "time": "2026-06-17T11:35:12Z",
    "cat": "economia",
    "tickers": [],
    "image": "https://www.infomoney.com.br/wp-content/uploads/2026/03/Ibovespa-ao-vivo-bolsa-de-valores-7.png?fit=300%2C186&amp;quality=70&amp;strip=all"
  },
  "featured": [
    {
      "title": "Bitcoin (BTC) cai antes do ‘Teste de Warsh’ no Banco Central; veja preços das criptomoedas nesta quarta-feira (17)",
      "summary": "O Bitcoin (BTC) é negociado na casa dos US$ 64,8 mil na manhã desta quarta-feira (17), com uma queda de cerca de 2% nas últimas 24h. O mercado global de criptomoedas opera no vermelho na manhã de hoje, com alguns tokens ",
      "source": "Money Times",
      "url": "https://www.moneytimes.com.br/bom-dia-bitcoin-btc-criptomoedas-precos-hoje-rens-170626/",
      "time": "2026-06-17T11:19:04Z",
      "cat": "cripto",
      "tickers": [
        "BTC"
      ],
      "image": "https://www.moneytimes.com.br/uploads/2026/04/kevin-warsh-fed-eua-.jpg"
    },
    {
      "title": "À espera do Fed: inflação, emprego e PIB dão pistas sobre o futuro dos juros nos EUA",
      "summary": "A decisão de juros do Federal Reserve desta quarta-feira (17) deve manter os investidores globais em compasso de espera. A expectativa amplamente majoritária do mercado é de manutenção da taxa básica americana no interva",
      "source": "Money Times",
      "url": "https://www.moneytimes.com.br/a-espera-do-fed-inflacao-emprego-e-pib-dao-pistas-sobre-o-futuro-dos-juros-nos-eua-jcav/",
      "time": "2026-06-17T11:00:00Z",
      "cat": "economia",
      "tickers": [],
      "image": "https://www.moneytimes.com.br/uploads/2025/07/fomc-federal-reserve-fed-juros-eua-estados-unidos.jpg"
    }
  ],
  "all": [
    {
      "title": "Ibovespa Hoje Ao Vivo: Confira o que movimenta Bolsa, Dólar e Juros nesta quarta",
      "summary": "Índices futuros dos EUA operam sem força em dia de decisão do Fed",
      "source": "InfoMoney",
      "url": "https://www.infomoney.com.br/mercados/ibovespa-hoje-bolsa-de-valores-ao-vivo-17062026/",
      "time": "2026-06-17T11:35:12Z",
      "cat": "economia",
      "tickers": [],
      "image": "https://www.infomoney.com.br/wp-content/uploads/2026/03/Ibovespa-ao-vivo-bolsa-de-valores-7.png?fit=300%2C186&amp;quality=70&amp;strip=all"
    },
    {
      "title": "Raízen, WEG, Jalles Machado, B3, PRIO e mais ações para acompanhar hoje",
      "summary": "Confira os principais destaques do noticiário corporativo desta quarta-feira",
      "source": "InfoMoney",
      "url": "https://www.infomoney.com.br/mercados/raizen-weg-jalles-machado-b3-prio-e-mais-acoes-para-acompanhar-hoje/",
      "time": "2026-06-17T11:32:14Z",
      "cat": "acoes",
      "tickers": [],
      "image": "https://www.infomoney.com.br/wp-content/uploads/2025/11/Captura-de-tela-2025-11-12-130824.png?fit=300%2C199&amp;quality=70&amp;strip=all"
    },
    {
      "title": "Alupar (ALUP11) pagará R$ 69,2 milhões em dividendos em 6 de julho",
      "summary": "Terão direito aos dividendos os investidores com posição acionária ao fim do pregão de 14 de maio de 2026",
      "source": "InfoMoney",
      "url": "https://www.infomoney.com.br/mercados/alupar-alup11-pagara-r-692-milhoes-em-dividendos-em-6-de-julho/",
      "time": "2026-06-17T11:26:42Z",
      "cat": "fundos",
      "tickers": [
        "ALUP11"
      ],
      "image": "https://www.infomoney.com.br/wp-content/uploads/2024/12/graph-163509_1920.jpg?fit=300%2C169&amp;quality=70&amp;strip=all"
    },
    {
      "title": "Telefônica Brasil (VIVT3) aprova incorporação da Fibrasil",
      "summary": "Fibrasil será extinta e todo o seu patrimônio será sucedido pela Telefônica Brasil",
      "source": "InfoMoney",
      "url": "https://www.infomoney.com.br/mercados/telefonica-brasil-vivt3-aprova-incorporacao-da-fibrasil/",
      "time": "2026-06-17T11:12:29Z",
      "cat": "acoes",
      "tickers": [
        "VIVT3"
      ],
      "image": "https://www.infomoney.com.br/wp-content/uploads/2019/06/telefonica_bloomberg.jpg?fit=300%2C204&amp;quality=70&amp;strip=all"
    },
    {
      "title": "Ações da BMW atingem mínimas de 2020 após alerta sobre lucros",
      "summary": "É um mau começo para o presidente-executivo Milan Nedeljkovic, que assumiu o cargo no ⁠mês passado, substituindo ​o líder de ​longa data Oliver Zipse",
      "source": "InfoMoney",
      "url": "https://www.infomoney.com.br/mercados/acoes-da-bmw-atingem-minimas-de-2020-apos-alerta-sobre-lucros/",
      "time": "2026-06-17T11:07:14Z",
      "cat": "acoes",
      "tickers": [],
      "image": "https://www.infomoney.com.br/wp-content/uploads/2024/10/2024-10-04T193856Z_1_LYNXMPEK930PM_RTROPTP_4_BMW-OUTLOOK.jpg?fit=300%2C210&amp;quality=70&amp;strip=all"
    },
    {
      "title": "Líderes do G7 exigem cessar-fogo no Líbano e acolhem com satisfação acordo com Irã",
      "summary": "Os líderes se reuniram para uma cúpula na cidade francesa de Evian-les-Bains, às margens do Lago Genebra",
      "source": "InfoMoney",
      "url": "https://www.infomoney.com.br/mundo/lideres-do-g7-exigem-cessar-fogo-no-libano-e-acolhem-com-satisfacao-acordo-com-ira/",
      "time": "2026-06-17T11:03:56Z",
      "cat": "acoes",
      "tickers": [],
      "image": "https://www.infomoney.com.br/wp-content/uploads/2026/06/2026-06-15T084636Z_1_LYNXMPEM5E0P1_RTROPTP_4_G7-SUMMIT-GROUP.jpg?fit=300%2C142&amp;quality=70&amp;strip=all"
    },
    {
      "title": "Jalles Machado (JALL3) tem prejuízo de R$ 50,9 mi no 4T, alta anual de 498,8%",
      "summary": "A receita líquida totalizou R$ 487,8 milhões",
      "source": "InfoMoney",
      "url": "https://www.infomoney.com.br/mercados/jalles-machado-jall3-resultados-quarto-trimestre-2025/",
      "time": "2026-06-17T11:02:25Z",
      "cat": "acoes",
      "tickers": [],
      "image": "https://www.infomoney.com.br/wp-content/uploads/2019/06/jalles-machado.jpg?fit=300%2C182&amp;quality=70&amp;strip=all"
    },
    {
      "title": "Ações da BMW caem ao menor nível desde 2020 após alerta sobre lucros",
      "summary": "As ações da montadora alemã de luxo BMW recuavam cerca de 7% na bolsa de valores de Frankfurt, na Alemanha, após a empresa ter divulgado, na noite de terça-feira (16), um alerta sobre os lucros que, segundo alguns analis",
      "source": "Money Times",
      "url": "https://www.moneytimes.com.br/acoes-da-bmw-caem-ao-menor-nivel-desde-2020-apos-alerta-sobre-lucros-igdl/",
      "time": "2026-06-17T11:23:36Z",
      "cat": "acoes",
      "tickers": [],
      "image": "https://www.moneytimes.com.br/uploads/2022/02/img-3-bmweletric2022.jpg"
    },
    {
      "title": "Engie Brasil (EGIE3) detalha acordo sobre participação na Jirau financiado por aumento de capital de R$ 5,74 bi",
      "summary": "A Engie Brasil (EGIE3) detalhou, em um documento apresentado à Comissão de Valores Mobiliários (CVM) na noite de terça-feira (16), os termos de um acordo para adquirir uma participação de 40% na usina hidrelétrica de Jir",
      "source": "Money Times",
      "url": "https://www.moneytimes.com.br/engie-brasil-detalha-acordo-sobre-participacao-na-jirau-financiado-por-aumento-de-capital-de-r-574-bi-lmrs/",
      "time": "2026-06-17T11:19:31Z",
      "cat": "acoes",
      "tickers": [
        "EGIE3"
      ],
      "image": "https://www.moneytimes.com.br/uploads/2024/08/engie-brasil-egie3.webp"
    },
    {
      "title": "Bitcoin (BTC) cai antes do ‘Teste de Warsh’ no Banco Central; veja preços das criptomoedas nesta quarta-feira (17)",
      "summary": "O Bitcoin (BTC) é negociado na casa dos US$ 64,8 mil na manhã desta quarta-feira (17), com uma queda de cerca de 2% nas últimas 24h. O mercado global de criptomoedas opera no vermelho na manhã de hoje, com alguns tokens ",
      "source": "Money Times",
      "url": "https://www.moneytimes.com.br/bom-dia-bitcoin-btc-criptomoedas-precos-hoje-rens-170626/",
      "time": "2026-06-17T11:19:04Z",
      "cat": "cripto",
      "tickers": [
        "BTC"
      ],
      "image": "https://www.moneytimes.com.br/uploads/2026/04/kevin-warsh-fed-eua-.jpg"
    },
    {
      "title": "Conselho da Telefônica Brasil (VIVT3) aprova incorporação da FiBrasil; veja detalhes",
      "summary": "O conselho de administração da Telefônica Brasil (VIVT3), dona da Vivo, aprovou a proposta de incorporação da subsidiária FiBrasil e convocação de Assembleia Geral Extraordinária da companhia para o dia 1 de julho de 202",
      "source": "Money Times",
      "url": "https://www.moneytimes.com.br/conselho-da-telefonica-brasil-vivt3-aprova-incorporacao-da-fibrasil-veja-detalhes-lmrs/",
      "time": "2026-06-17T11:14:05Z",
      "cat": "acoes",
      "tickers": [
        "VIVT3"
      ],
      "image": "https://www.moneytimes.com.br/uploads/2024/08/telefonica-vivt3-day-trade.jpg"
    },
    {
      "title": "À espera do Fed: inflação, emprego e PIB dão pistas sobre o futuro dos juros nos EUA",
      "summary": "A decisão de juros do Federal Reserve desta quarta-feira (17) deve manter os investidores globais em compasso de espera. A expectativa amplamente majoritária do mercado é de manutenção da taxa básica americana no interva",
      "source": "Money Times",
      "url": "https://www.moneytimes.com.br/a-espera-do-fed-inflacao-emprego-e-pib-dao-pistas-sobre-o-futuro-dos-juros-nos-eua-jcav/",
      "time": "2026-06-17T11:00:00Z",
      "cat": "economia",
      "tickers": [],
      "image": "https://www.moneytimes.com.br/uploads/2025/07/fomc-federal-reserve-fed-juros-eua-estados-unidos.jpg"
    },
    {
      "title": "Fundo imobiliário mira captação de até R$ 2,3 bilhões em nova emissão de cotas; IFIX recua",
      "summary": "O fundo imobiliário Suno Energias Limpas (SNEL11) aprovou a realização de sua 5ª emissão de cotas, com volume inicial de R$ 1,84 bilhão, mostra fato relevante divulgado ao mercado nessa terça-feira (16). De acordo com o ",
      "source": "Money Times",
      "url": "https://www.moneytimes.com.br/fundo-imobiliario-mira-captacao-de-ate-r-23-bilhoes-em-nova-emissao-de-cotas-ifix-recua-igdl/",
      "time": "2026-06-17T10:56:53Z",
      "cat": "fundos",
      "tickers": [],
      "image": "https://www.moneytimes.com.br/uploads/2025/04/fundos-imobiliarios-carteira-recomendada-.jpg"
    },
    {
      "title": "SNEL11 negocia mais de R$ 10 mi enquanto IPO da SpaceX reforça tese energética",
      "summary": "O fundo imobiliário SNEL11 voltou a ganhar destaque na B3 ao somar mais de R$ 10,3 milhões em negociações nesta terça-feira (16), repetindo o forte volume observado no pregão anterior. O interesse ocorre em um momento em",
      "source": "Suno",
      "url": "https://www.suno.com.br/noticias/snel11-negocia-mais-de-r-10-mi-enquanto-ipo-da-spacex-reforca-tese-energetica/",
      "time": "2026-06-16T22:05:17Z",
      "cat": "acoes",
      "tickers": [],
      "image": null
    },
    {
      "title": "IFIX recua para 3.824,21 pontos e fecha em queda de 0,23%",
      "summary": "O IFIX fechou o pregão desta terça-feira (16) em 3.824,21 pontos, queda de 0,23% — retração de 8,94 pontos ante o encerramento anterior, quando marcara 3.833,15 pontos. Ao longo do dia, o principal índice de fundos imobi",
      "source": "Suno",
      "url": "https://www.suno.com.br/noticias/ifix-recua-para-3-82421-pontos-e-fecha-em-queda-de-023/",
      "time": "2026-06-16T22:05:09Z",
      "cat": "fundos",
      "tickers": [],
      "image": null
    },
    {
      "title": "Rede D’Or (RDOR3): família controladora coloca dinheiro de volta na ação",
      "summary": "A Rede D’Or (RDOR3) voltou ao radar dos analistas após um relatório destacar o movimento da família Moll, controladora da companhia, de reinvestir parte relevante dos recursos recebidos desde o IPO na própria empresa. Se",
      "source": "Suno",
      "url": "https://www.suno.com.br/noticias/rede-dor-rdor3-familia-moll-acoes-btg-mt/",
      "time": "2026-06-16T20:15:15Z",
      "cat": "acoes",
      "tickers": [
        "RDOR3"
      ],
      "image": null
    },
    {
      "title": "FII ZAGH11 atrai investidores e levanta R$ 136,9 milhões em nova oferta",
      "summary": "O fundo imobiliário (FII) ZAGH11 encerrou o período de subscrição de sua terceira emissão de cotas, concluindo uma captação total de aproximadamente R$ 136,9 milhões. Segundo comunicado ao mercado, o volume superou o mon",
      "source": "Suno",
      "url": "https://www.suno.com.br/noticias/fii-zagh11-atrai-investidores-e-levanta-r-1369-milhoes-em-nova-oferta/",
      "time": "2026-06-16T20:15:05Z",
      "cat": "fundos",
      "tickers": [],
      "image": null
    },
    {
      "title": "Superquarta sem festa? Analistas veem Fed travado e Copom ainda sob pressão",
      "summary": "O Fed e Copom chegam à Superquarta em meio a um alívio nos mercados globais, após sinais de solução entre Washington e Teerã reduzirem a pressão sobre o petróleo. Mas, para analistas, esse respiro ainda não muda o cenári",
      "source": "Suno",
      "url": "https://www.suno.com.br/noticias/copom-fed-superquarta-juros-selic-analistas-mt/",
      "time": "2026-06-16T18:05:00Z",
      "cat": "economia",
      "tickers": [],
      "image": null
    },
    {
      "title": "Braskem (BRKM5) afunda na Bolsa após virar ré no caso Maceió",
      "summary": "A Braskem (BRKM5) liderava as perdas do Ibovespa nesta terça-feira (16), depois que a Justiça Federal em Alagoas aceitou denúncia do Ministério Público Federal (MPF) e tornou a companhia ré por crimes ambientais relacion",
      "source": "Suno",
      "url": "https://www.suno.com.br/noticias/braskem-brkm5-cai-re-justica-maceio-mt/",
      "time": "2026-06-16T17:15:07Z",
      "cat": "acoes",
      "tickers": [],
      "image": null
    },
    {
      "title": "Irã ameaça reação militar após novos ataques de Israel no Líbano",
      "summary": "Ameaça ocorre enquanto EUA e Irã se preparam para assinar acordo na Suíça",
      "source": "Exame",
      "url": "https://exame.com/mundo/ira-ameaca-reacao-militar-apos-novos-ataques-de-israel-no-libano/",
      "time": "2026-06-17T08:43:31Z",
      "cat": "economia",
      "tickers": [],
      "image": "https://classic.exame.com/wp-content/uploads/2026/05/Guerra-Ira-Eua.jpg"
    },
    {
      "title": "Guerra no Oriente Médio derruba previsão para petróleo, diz AIE",
      "summary": "Bloqueio do Estreito de Ormuz pressionou oferta, consumo e estoques globais de petróleo",
      "source": "Exame",
      "url": "https://exame.com/mundo/guerra-no-oriente-medio-derruba-previsao-para-petroleo-diz-aie/",
      "time": "2026-06-17T08:36:39Z",
      "cat": "internacional",
      "tickers": [],
      "image": "https://classic.exame.com/wp-content/uploads/2026/03/petroleo_crise.jpg"
    },
    {
      "title": "Irã retoma exportação de petróleo após dois meses de bloqueio",
      "summary": "Dois superpetroleiros deixaram águas iranianas após avanço das negociações entre Teerã e Washington",
      "source": "Exame",
      "url": "https://exame.com/mundo/ira-retoma-exportacao-de-petroleo-apos-dois-meses-de-bloqueio/",
      "time": "2026-06-17T08:31:19Z",
      "cat": "internacional",
      "tickers": [],
      "image": "https://classic.exame.com/wp-content/uploads/2026/04/barrels-oil-high-seas-created-with-generative-ai-technology.jpg"
    },
    {
      "title": "Tramitação da PEC do fim da escala 6x1 deve ficar para julho no Senado",
      "summary": "Presidente da CCJ prevê definição da tramitação apenas na primeira quinzena de julho.",
      "source": "Exame",
      "url": "https://exame.com/brasil/tramitacao-da-pec-do-fim-da-escala-6x1-deve-ficar-para-julho-no-senado/",
      "time": "2026-06-17T08:19:30Z",
      "cat": "economia",
      "tickers": [],
      "image": "https://classic.exame.com/wp-content/uploads/2026/03/Senado.jpg"
    },
    {
      "title": "Portugal vai ganhar a Copa do Mundo? Veja chances de Cristiano Ronaldo ser campeão",
      "summary": "Com Cristiano Ronaldo na sexta Copa da carreira, Portugal aparece entre as 10 seleções com maior chance de conquistar o Mundial",
      "source": "Exame",
      "url": "https://exame.com/esporte/portugal-vai-ganhar-a-copa-do-mundo-veja-chances-de-cristiano-ronaldo-ser-campeao/",
      "time": "2026-06-17T08:14:13Z",
      "cat": "economia",
      "tickers": [],
      "image": "https://classic.exame.com/wp-content/uploads/2022/11/GettyImages-1444540503.jpg"
    },
    {
      "title": "Ações da Figma sobem 5% após Citi iniciar cobertura com recomendação de compra",
      "summary": "",
      "source": "Investing.com",
      "url": "https://br.investing.com/news/stock-market-news/acoes-da-figma-sobem-5-apos-citi-iniciar-cobertura-com-recomendacao-de-compra-93CH-1975847",
      "time": "2026-06-17T11:31:00Z",
      "cat": "analise",
      "tickers": [],
      "image": "https://i-invdn-com.investing.com/news/world_news_2_108x81.jpg"
    },
    {
      "title": "Por que as ações da Monolithic Power Systems estão subindo hoje?",
      "summary": "",
      "source": "Investing.com",
      "url": "https://br.investing.com/news/stock-market-news/por-que-as-acoes-da-monolithic-power-systems-estao-subindo-hoje-93CH-1975842",
      "time": "2026-06-17T11:27:42Z",
      "cat": "internacional",
      "tickers": [],
      "image": "https://i-invdn-com.investing.com/news/world_news_2_108x81.jpg"
    },
    {
      "title": "Ações da Palladyne AI sobem após contratos com o Exército dos EUA",
      "summary": "",
      "source": "Investing.com",
      "url": "https://br.investing.com/news/stock-market-news/acoes-da-palladyne-ai-sobem-apos-contratos-com-o-exercito-dos-eua-93CH-1975841",
      "time": "2026-06-17T11:27:35Z",
      "cat": "internacional",
      "tickers": [],
      "image": "https://i-invdn-com.investing.com/news/world_news_2_108x81.jpg"
    },
    {
      "title": "Por que as ações da Broadcom estão subindo hoje?",
      "summary": "",
      "source": "Investing.com",
      "url": "https://br.investing.com/news/stock-market-news/por-que-as-acoes-da-broadcom-estao-subindo-hoje-93CH-1975840",
      "time": "2026-06-17T11:27:10Z",
      "cat": "internacional",
      "tickers": [],
      "image": "https://i-invdn-com.investing.com/news/world_news_2_108x81.jpg"
    },
    {
      "title": "MSC nega especulações sobre possível participação na Hapag-Lloyd",
      "summary": "",
      "source": "Investing.com",
      "url": "https://br.investing.com/news/stock-market-news/msc-nega-especulacoes-sobre-possivel-participacao-na-hapaglloyd-93CH-1975839",
      "time": "2026-06-17T11:25:52Z",
      "cat": "internacional",
      "tickers": [],
      "image": "https://i-invdn-com.investing.com/news/world_news_2_108x81.jpg"
    },
    {
      "title": "HSBC Brasil quer chegar a top 10 do banco no mundo, diz CEO",
      "summary": "",
      "source": "Investing.com",
      "url": "https://br.investing.com/news/stock-market-news/hsbc-brasil-quer-chegar-a-top-10-do-banco-no-mundo-diz-ceo-1975836",
      "time": "2026-06-17T11:22:11Z",
      "cat": "internacional",
      "tickers": [],
      "image": "https://i-invdn-com.investing.com/trkd-images/LYNXMPEM5G0WV_1200_L.jpg"
    },
    {
      "title": "Ações da ClearPoint Neuro disparam após aprovação da FDA para concorrente",
      "summary": "",
      "source": "Investing.com",
      "url": "https://br.investing.com/news/stock-market-news/acoes-da-clearpoint-neuro-disparam-apos-aprovacao-da-fda-para-concorrente-93CH-1975835",
      "time": "2026-06-17T11:22:07Z",
      "cat": "internacional",
      "tickers": [],
      "image": "https://i-invdn-com.investing.com/news/world_news_2_108x81.jpg"
    },
    {
      "title": "Ação da uniQure deve subir após FDA aprovar via BLA para AMT-130",
      "summary": "",
      "source": "Investing.com",
      "url": "https://br.investing.com/news/stock-market-news/acao-da-uniqure-deve-subir-apos-fda-aprovar-via-bla-para-amt130-93CH-1975830",
      "time": "2026-06-17T11:16:42Z",
      "cat": "internacional",
      "tickers": [],
      "image": "https://i-invdn-com.investing.com/news/world_news_2_108x81.jpg"
    },
    {
      "title": "Ações da Ormat Technologies caem após classificação ’underperform’ da Bernstein",
      "summary": "",
      "source": "Investing.com",
      "url": "https://br.investing.com/news/stock-market-news/acoes-da-ormat-technologies-caem-apos-classificacao-underperform-da-bernstein-93CH-1975815",
      "time": "2026-06-17T11:13:22Z",
      "cat": "internacional",
      "tickers": [],
      "image": "https://i-invdn-com.investing.com/news/world_news_2_108x81.jpg"
    }
  ],
  "atualizado_em": "17/06/2026 11:48"
}